annotations/types.py
config.py
dv_mcp_server.py
services/dv_api.py
develocity_mcp_server-0.6.2.dist-info/METADATA
develocity_mcp_server-0.6.2.dist-info/WHEEL
develocity_mcp_server-0.6.2.dist-info/entry_points.txt
develocity_mcp_server-0.6.2.dist-info/RECORD
