Metadata-Version: 2.1
Name: develocity-mcp-server
Version: 0.6.2
Summary: An MCP server for interacting with Develocity build data.
Author: develocity
Requires-Python: >=3.12,<4.0
Classifier: Programming Language :: Python :: 3
Classifier: Programming Language :: Python :: 3.12
Requires-Dist: fastmcp (>=2.10.1,<3.0.0)
Requires-Dist: pydantic (>=2.11.7,<3.0.0)
Requires-Dist: requests (>=2.32.4,<3.0.0)
